{
  "generated_at": "2026-07-16T01:35:08.597110+00:00",
  "model": "Ridge Regression (sklearn)",
  "features": [
    "hour_sin",
    "hour_cos",
    "day_sin",
    "day_cos",
    "temperature",
    "humidity",
    "pressure",
    "windspeed"
  ],
  "cities": [
    {
      "city": "Dar es Salaam",
      "city_key": "dar_es_salaam",
      "mae": 0.21930205904869896,
      "data_points": 934,
      "next_hour_prediction": 20.71192655373356,
      "model_type": "ridge_regression"
    },
    {
      "city": "Dodoma",
      "city_key": "dodoma",
      "mae": 0.2538456264453156,
      "data_points": 972,
      "next_hour_prediction": 16.139592238067003,
      "model_type": "ridge_regression"
    },
    {
      "city": "Arusha",
      "city_key": "arusha",
      "mae": 0.259769027874502,
      "data_points": 977,
      "next_hour_prediction": 14.40339207069372,
      "model_type": "ridge_regression"
    },
    {
      "city": "Mwanza",
      "city_key": "mwanza",
      "mae": 0.3692187202485521,
      "data_points": 977,
      "next_hour_prediction": 19.990144566397163,
      "model_type": "ridge_regression"
    },
    {
      "city": "Zanzibar",
      "city_key": "zanzibar",
      "mae": 0.1179474034407585,
      "data_points": 975,
      "next_hour_prediction": 22.776959319679786,
      "model_type": "ridge_regression"
    }
  ]
}