{
  "generated_at": "2026-07-20T16:50:09.396102+00:00",
  "model": "Ridge Regression (sklearn)",
  "features": [
    "hour_sin",
    "hour_cos",
    "day_sin",
    "day_cos",
    "temperature",
    "humidity",
    "pressure",
    "windspeed"
  ],
  "cities": [
    {
      "city": "Dar es Salaam",
      "city_key": "dar_es_salaam",
      "mae": 0.1721108779749351,
      "data_points": 1370,
      "next_hour_prediction": 23.558657682517087,
      "model_type": "ridge_regression"
    },
    {
      "city": "Dodoma",
      "city_key": "dodoma",
      "mae": 0.2545006255324576,
      "data_points": 1417,
      "next_hour_prediction": 20.97048692285724,
      "model_type": "ridge_regression"
    },
    {
      "city": "Arusha",
      "city_key": "arusha",
      "mae": 0.1885113883387424,
      "data_points": 1422,
      "next_hour_prediction": 18.389784345240525,
      "model_type": "ridge_regression"
    },
    {
      "city": "Mwanza",
      "city_key": "mwanza",
      "mae": 0.2220962661169133,
      "data_points": 1422,
      "next_hour_prediction": 22.65089253677388,
      "model_type": "ridge_regression"
    },
    {
      "city": "Zanzibar",
      "city_key": "zanzibar",
      "mae": 0.13834418751672667,
      "data_points": 1419,
      "next_hour_prediction": 23.287743399914834,
      "model_type": "ridge_regression"
    }
  ]
}