{
  "generated_at": "2026-07-18T19:05:08.282639+00:00",
  "model": "Ridge Regression (sklearn)",
  "features": [
    "hour_sin",
    "hour_cos",
    "day_sin",
    "day_cos",
    "temperature",
    "humidity",
    "pressure",
    "windspeed"
  ],
  "cities": [
    {
      "city": "Dar es Salaam",
      "city_key": "dar_es_salaam",
      "mae": 0.22578041562754161,
      "data_points": 1188,
      "next_hour_prediction": 22.29520282309052,
      "model_type": "ridge_regression"
    },
    {
      "city": "Dodoma",
      "city_key": "dodoma",
      "mae": 0.2748651193592656,
      "data_points": 1234,
      "next_hour_prediction": 17.150033286160077,
      "model_type": "ridge_regression"
    },
    {
      "city": "Arusha",
      "city_key": "arusha",
      "mae": 0.19994668056417253,
      "data_points": 1239,
      "next_hour_prediction": 17.496684161639106,
      "model_type": "ridge_regression"
    },
    {
      "city": "Mwanza",
      "city_key": "mwanza",
      "mae": 0.2914748952824962,
      "data_points": 1239,
      "next_hour_prediction": 21.674461582974626,
      "model_type": "ridge_regression"
    },
    {
      "city": "Zanzibar",
      "city_key": "zanzibar",
      "mae": 0.09791051996511492,
      "data_points": 1237,
      "next_hour_prediction": 22.7772302932553,
      "model_type": "ridge_regression"
    }
  ]
}