{
  "generated_at": "2026-07-19T22:35:08.863704+00:00",
  "model": "Ridge Regression (sklearn)",
  "features": [
    "hour_sin",
    "hour_cos",
    "day_sin",
    "day_cos",
    "temperature",
    "humidity",
    "pressure",
    "windspeed"
  ],
  "cities": [
    {
      "city": "Dar es Salaam",
      "city_key": "dar_es_salaam",
      "mae": 0.17459831514288618,
      "data_points": 1298,
      "next_hour_prediction": 22.440320041854008,
      "model_type": "ridge_regression"
    },
    {
      "city": "Dodoma",
      "city_key": "dodoma",
      "mae": 0.25705664721028404,
      "data_points": 1344,
      "next_hour_prediction": 15.746462309275046,
      "model_type": "ridge_regression"
    },
    {
      "city": "Arusha",
      "city_key": "arusha",
      "mae": 0.19871980218244165,
      "data_points": 1349,
      "next_hour_prediction": 14.760787504146567,
      "model_type": "ridge_regression"
    },
    {
      "city": "Mwanza",
      "city_key": "mwanza",
      "mae": 0.2252981997600231,
      "data_points": 1349,
      "next_hour_prediction": 19.866083982888863,
      "model_type": "ridge_regression"
    },
    {
      "city": "Zanzibar",
      "city_key": "zanzibar",
      "mae": 0.11381712782789487,
      "data_points": 1347,
      "next_hour_prediction": 22.618304192018122,
      "model_type": "ridge_regression"
    }
  ]
}