{
  "generated_at": "2026-07-24T01:35:09.801172+00:00",
  "model": "Ridge Regression (sklearn)",
  "features": [
    "hour_sin",
    "hour_cos",
    "day_sin",
    "day_cos",
    "temperature",
    "humidity",
    "pressure",
    "windspeed"
  ],
  "cities": [
    {
      "city": "Dar es Salaam",
      "city_key": "dar_es_salaam",
      "mae": 0.1546529661073006,
      "data_points": 1681,
      "next_hour_prediction": 21.82784075093832,
      "model_type": "ridge_regression"
    },
    {
      "city": "Dodoma",
      "city_key": "dodoma",
      "mae": 0.2252348161872373,
      "data_points": 1738,
      "next_hour_prediction": 15.497956484400653,
      "model_type": "ridge_regression"
    },
    {
      "city": "Arusha",
      "city_key": "arusha",
      "mae": 0.16453047819164274,
      "data_points": 1745,
      "next_hour_prediction": 14.203424391449724,
      "model_type": "ridge_regression"
    },
    {
      "city": "Mwanza",
      "city_key": "mwanza",
      "mae": 0.2192666758131517,
      "data_points": 1745,
      "next_hour_prediction": 19.157098047884126,
      "model_type": "ridge_regression"
    },
    {
      "city": "Zanzibar",
      "city_key": "zanzibar",
      "mae": 0.12134567932994257,
      "data_points": 1742,
      "next_hour_prediction": 22.81298766805063,
      "model_type": "ridge_regression"
    }
  ]
}