{
  "generated_at": "2026-07-20T18:05:08.787183+00:00",
  "model": "Ridge Regression (sklearn)",
  "features": [
    "hour_sin",
    "hour_cos",
    "day_sin",
    "day_cos",
    "temperature",
    "humidity",
    "pressure",
    "windspeed"
  ],
  "cities": [
    {
      "city": "Dar es Salaam",
      "city_key": "dar_es_salaam",
      "mae": 0.1714481175858977,
      "data_points": 1374,
      "next_hour_prediction": 23.082624058691366,
      "model_type": "ridge_regression"
    },
    {
      "city": "Dodoma",
      "city_key": "dodoma",
      "mae": 0.2570877569328662,
      "data_points": 1422,
      "next_hour_prediction": 19.23511860463043,
      "model_type": "ridge_regression"
    },
    {
      "city": "Arusha",
      "city_key": "arusha",
      "mae": 0.19104246603758723,
      "data_points": 1427,
      "next_hour_prediction": 18.322548515815477,
      "model_type": "ridge_regression"
    },
    {
      "city": "Mwanza",
      "city_key": "mwanza",
      "mae": 0.21991669004205966,
      "data_points": 1427,
      "next_hour_prediction": 22.21717228257639,
      "model_type": "ridge_regression"
    },
    {
      "city": "Zanzibar",
      "city_key": "zanzibar",
      "mae": 0.13830442709850937,
      "data_points": 1424,
      "next_hour_prediction": 22.78274116762293,
      "model_type": "ridge_regression"
    }
  ]
}