{
  "generated_at": "2026-07-20T17:35:09.895829+00:00",
  "model": "Ridge Regression (sklearn)",
  "features": [
    "hour_sin",
    "hour_cos",
    "day_sin",
    "day_cos",
    "temperature",
    "humidity",
    "pressure",
    "windspeed"
  ],
  "cities": [
    {
      "city": "Dar es Salaam",
      "city_key": "dar_es_salaam",
      "mae": 0.17155667058394397,
      "data_points": 1372,
      "next_hour_prediction": 23.314221782600384,
      "model_type": "ridge_regression"
    },
    {
      "city": "Dodoma",
      "city_key": "dodoma",
      "mae": 0.25500387677890707,
      "data_points": 1420,
      "next_hour_prediction": 19.723386271354695,
      "model_type": "ridge_regression"
    },
    {
      "city": "Arusha",
      "city_key": "arusha",
      "mae": 0.189434497429471,
      "data_points": 1425,
      "next_hour_prediction": 18.300729246095226,
      "model_type": "ridge_regression"
    },
    {
      "city": "Mwanza",
      "city_key": "mwanza",
      "mae": 0.22072635560975742,
      "data_points": 1425,
      "next_hour_prediction": 22.400722992474407,
      "model_type": "ridge_regression"
    },
    {
      "city": "Zanzibar",
      "city_key": "zanzibar",
      "mae": 0.13820507882203445,
      "data_points": 1422,
      "next_hour_prediction": 22.90516307432878,
      "model_type": "ridge_regression"
    }
  ]
}