{
  "generated_at": "2026-07-10T21:20:09.258236+00:00",
  "model": "Ridge Regression (sklearn)",
  "features": [
    "hour_sin",
    "hour_cos",
    "day_sin",
    "day_cos",
    "temperature",
    "humidity",
    "pressure",
    "windspeed"
  ],
  "cities": [
    {
      "city": "Dar es Salaam",
      "city_key": "dar_es_salaam",
      "mae": 0.4385533667541114,
      "data_points": 447,
      "next_hour_prediction": 22.155238418983256,
      "model_type": "ridge_regression"
    },
    {
      "city": "Dodoma",
      "city_key": "dodoma",
      "mae": 0.5207028297810432,
      "data_points": 477,
      "next_hour_prediction": 16.55996140909783,
      "model_type": "ridge_regression"
    },
    {
      "city": "Arusha",
      "city_key": "arusha",
      "mae": 0.3676801496346627,
      "data_points": 481,
      "next_hour_prediction": 15.636639708876903,
      "model_type": "ridge_regression"
    },
    {
      "city": "Mwanza",
      "city_key": "mwanza",
      "mae": 0.4520135883604004,
      "data_points": 481,
      "next_hour_prediction": 21.3313833878881,
      "model_type": "ridge_regression"
    },
    {
      "city": "Zanzibar",
      "city_key": "zanzibar",
      "mae": 0.33567576198557597,
      "data_points": 480,
      "next_hour_prediction": 22.789154743177374,
      "model_type": "ridge_regression"
    }
  ]
}