{
  "generated_at": "2026-07-21T21:20:10.782720+00:00",
  "model": "Ridge Regression (sklearn)",
  "features": [
    "hour_sin",
    "hour_cos",
    "day_sin",
    "day_cos",
    "temperature",
    "humidity",
    "pressure",
    "windspeed"
  ],
  "cities": [
    {
      "city": "Dar es Salaam",
      "city_key": "dar_es_salaam",
      "mae": 0.19128775790265742,
      "data_points": 1481,
      "next_hour_prediction": 22.644456666346226,
      "model_type": "ridge_regression"
    },
    {
      "city": "Dodoma",
      "city_key": "dodoma",
      "mae": 0.24801831736707192,
      "data_points": 1531,
      "next_hour_prediction": 17.77426721160626,
      "model_type": "ridge_regression"
    },
    {
      "city": "Arusha",
      "city_key": "arusha",
      "mae": 0.19345796872000576,
      "data_points": 1536,
      "next_hour_prediction": 16.566396785875515,
      "model_type": "ridge_regression"
    },
    {
      "city": "Mwanza",
      "city_key": "mwanza",
      "mae": 0.2039967800367388,
      "data_points": 1536,
      "next_hour_prediction": 22.15044531762197,
      "model_type": "ridge_regression"
    },
    {
      "city": "Zanzibar",
      "city_key": "zanzibar",
      "mae": 0.14862695176587878,
      "data_points": 1533,
      "next_hour_prediction": 22.760535332489127,
      "model_type": "ridge_regression"
    }
  ]
}