{
  "generated_at": "2026-07-21T02:20:09.492098+00:00",
  "model": "Ridge Regression (sklearn)",
  "features": [
    "hour_sin",
    "hour_cos",
    "day_sin",
    "day_cos",
    "temperature",
    "humidity",
    "pressure",
    "windspeed"
  ],
  "cities": [
    {
      "city": "Dar es Salaam",
      "city_key": "dar_es_salaam",
      "mae": 0.17196845209023368,
      "data_points": 1407,
      "next_hour_prediction": 21.51074612040708,
      "model_type": "ridge_regression"
    },
    {
      "city": "Dodoma",
      "city_key": "dodoma",
      "mae": 0.26189448279193595,
      "data_points": 1455,
      "next_hour_prediction": 15.178414613270125,
      "model_type": "ridge_regression"
    },
    {
      "city": "Arusha",
      "city_key": "arusha",
      "mae": 0.19015413517467658,
      "data_points": 1460,
      "next_hour_prediction": 13.746762380064318,
      "model_type": "ridge_regression"
    },
    {
      "city": "Mwanza",
      "city_key": "mwanza",
      "mae": 0.21094515551739787,
      "data_points": 1460,
      "next_hour_prediction": 19.139825191676067,
      "model_type": "ridge_regression"
    },
    {
      "city": "Zanzibar",
      "city_key": "zanzibar",
      "mae": 0.15316638188441203,
      "data_points": 1457,
      "next_hour_prediction": 21.642112319283093,
      "model_type": "ridge_regression"
    }
  ]
}