{
  "generated_at": "2026-07-22T08:20:09.709557+00:00",
  "model": "Ridge Regression (sklearn)",
  "features": [
    "hour_sin",
    "hour_cos",
    "day_sin",
    "day_cos",
    "temperature",
    "humidity",
    "pressure",
    "windspeed"
  ],
  "cities": [
    {
      "city": "Dar es Salaam",
      "city_key": "dar_es_salaam",
      "mae": 0.17525394077679882,
      "data_points": 1525,
      "next_hour_prediction": 26.916108395921952,
      "model_type": "ridge_regression"
    },
    {
      "city": "Dodoma",
      "city_key": "dodoma",
      "mae": 0.25783714359724147,
      "data_points": 1574,
      "next_hour_prediction": 25.294073849247688,
      "model_type": "ridge_regression"
    },
    {
      "city": "Arusha",
      "city_key": "arusha",
      "mae": 0.17839142878818398,
      "data_points": 1580,
      "next_hour_prediction": 20.196199989317826,
      "model_type": "ridge_regression"
    },
    {
      "city": "Mwanza",
      "city_key": "mwanza",
      "mae": 0.21999208486672633,
      "data_points": 1580,
      "next_hour_prediction": 24.934099991019064,
      "model_type": "ridge_regression"
    },
    {
      "city": "Zanzibar",
      "city_key": "zanzibar",
      "mae": 0.14577363178358074,
      "data_points": 1577,
      "next_hour_prediction": 26.707196035817198,
      "model_type": "ridge_regression"
    }
  ]
}