{
  "generated_at": "2026-07-14T11:20:09.664598+00:00",
  "model": "Ridge Regression (sklearn)",
  "features": [
    "hour_sin",
    "hour_cos",
    "day_sin",
    "day_cos",
    "temperature",
    "humidity",
    "pressure",
    "windspeed"
  ],
  "cities": [
    {
      "city": "Dar es Salaam",
      "city_key": "dar_es_salaam",
      "mae": 0.2934274734007305,
      "data_points": 785,
      "next_hour_prediction": 26.069309794588612,
      "model_type": "ridge_regression"
    },
    {
      "city": "Dodoma",
      "city_key": "dodoma",
      "mae": 0.325379749945819,
      "data_points": 819,
      "next_hour_prediction": 26.22524725623026,
      "model_type": "ridge_regression"
    },
    {
      "city": "Arusha",
      "city_key": "arusha",
      "mae": 0.31716699144911725,
      "data_points": 824,
      "next_hour_prediction": 21.108678500537653,
      "model_type": "ridge_regression"
    },
    {
      "city": "Mwanza",
      "city_key": "mwanza",
      "mae": 0.5198083832789059,
      "data_points": 824,
      "next_hour_prediction": 26.574178655759653,
      "model_type": "ridge_regression"
    },
    {
      "city": "Zanzibar",
      "city_key": "zanzibar",
      "mae": 0.2488572647310901,
      "data_points": 822,
      "next_hour_prediction": 26.371862185911784,
      "model_type": "ridge_regression"
    }
  ]
}