{
  "generated_at": "2026-07-12T14:35:09.791903+00:00",
  "model": "Ridge Regression (sklearn)",
  "features": [
    "hour_sin",
    "hour_cos",
    "day_sin",
    "day_cos",
    "temperature",
    "humidity",
    "pressure",
    "windspeed"
  ],
  "cities": [
    {
      "city": "Dar es Salaam",
      "city_key": "dar_es_salaam",
      "mae": 0.3999878638082713,
      "data_points": 607,
      "next_hour_prediction": 24.815062104255276,
      "model_type": "ridge_regression"
    },
    {
      "city": "Dodoma",
      "city_key": "dodoma",
      "mae": 0.40815459421278144,
      "data_points": 640,
      "next_hour_prediction": 24.337318768009695,
      "model_type": "ridge_regression"
    },
    {
      "city": "Arusha",
      "city_key": "arusha",
      "mae": 0.30721163467075324,
      "data_points": 645,
      "next_hour_prediction": 20.81136978803554,
      "model_type": "ridge_regression"
    },
    {
      "city": "Mwanza",
      "city_key": "mwanza",
      "mae": 0.3003837628675292,
      "data_points": 645,
      "next_hour_prediction": 24.84470120057861,
      "model_type": "ridge_regression"
    },
    {
      "city": "Zanzibar",
      "city_key": "zanzibar",
      "mae": 0.2587232026828951,
      "data_points": 644,
      "next_hour_prediction": 24.92409317851697,
      "model_type": "ridge_regression"
    }
  ]
}