{
  "generated_at": "2026-07-23T08:05:09.213584+00:00",
  "model": "Ridge Regression (sklearn)",
  "features": [
    "hour_sin",
    "hour_cos",
    "day_sin",
    "day_cos",
    "temperature",
    "humidity",
    "pressure",
    "windspeed"
  ],
  "cities": [
    {
      "city": "Dar es Salaam",
      "city_key": "dar_es_salaam",
      "mae": 0.16126063060078932,
      "data_points": 1615,
      "next_hour_prediction": 27.157780540564108,
      "model_type": "ridge_regression"
    },
    {
      "city": "Dodoma",
      "city_key": "dodoma",
      "mae": 0.2712412651382268,
      "data_points": 1668,
      "next_hour_prediction": 24.08865332521232,
      "model_type": "ridge_regression"
    },
    {
      "city": "Arusha",
      "city_key": "arusha",
      "mae": 0.1573922234308599,
      "data_points": 1675,
      "next_hour_prediction": 19.276424953326583,
      "model_type": "ridge_regression"
    },
    {
      "city": "Mwanza",
      "city_key": "mwanza",
      "mae": 0.20580155149752546,
      "data_points": 1675,
      "next_hour_prediction": 26.40388011549814,
      "model_type": "ridge_regression"
    },
    {
      "city": "Zanzibar",
      "city_key": "zanzibar",
      "mae": 0.12402808710344178,
      "data_points": 1672,
      "next_hour_prediction": 26.718207883748285,
      "model_type": "ridge_regression"
    }
  ]
}