{
  "generated_at": "2026-07-19T11:50:09.411180+00:00",
  "model": "Ridge Regression (sklearn)",
  "features": [
    "hour_sin",
    "hour_cos",
    "day_sin",
    "day_cos",
    "temperature",
    "humidity",
    "pressure",
    "windspeed"
  ],
  "cities": [
    {
      "city": "Dar es Salaam",
      "city_key": "dar_es_salaam",
      "mae": 0.17724497556003513,
      "data_points": 1255,
      "next_hour_prediction": 27.042325657371634,
      "model_type": "ridge_regression"
    },
    {
      "city": "Dodoma",
      "city_key": "dodoma",
      "mae": 0.2421218158252188,
      "data_points": 1301,
      "next_hour_prediction": 27.876907393755808,
      "model_type": "ridge_regression"
    },
    {
      "city": "Arusha",
      "city_key": "arusha",
      "mae": 0.18453537530597738,
      "data_points": 1306,
      "next_hour_prediction": 23.66173489072218,
      "model_type": "ridge_regression"
    },
    {
      "city": "Mwanza",
      "city_key": "mwanza",
      "mae": 0.255051399471318,
      "data_points": 1306,
      "next_hour_prediction": 25.649929122001048,
      "model_type": "ridge_regression"
    },
    {
      "city": "Zanzibar",
      "city_key": "zanzibar",
      "mae": 0.11110758689598102,
      "data_points": 1304,
      "next_hour_prediction": 26.316936199542045,
      "model_type": "ridge_regression"
    }
  ]
}