{
  "generated_at": "2026-07-22T04:20:09.890309+00:00",
  "model": "Ridge Regression (sklearn)",
  "features": [
    "hour_sin",
    "hour_cos",
    "day_sin",
    "day_cos",
    "temperature",
    "humidity",
    "pressure",
    "windspeed"
  ],
  "cities": [
    {
      "city": "Dar es Salaam",
      "city_key": "dar_es_salaam",
      "mae": 0.20240676555920745,
      "data_points": 1509,
      "next_hour_prediction": 22.645032751329733,
      "model_type": "ridge_regression"
    },
    {
      "city": "Dodoma",
      "city_key": "dodoma",
      "mae": 0.24806589991690267,
      "data_points": 1559,
      "next_hour_prediction": 16.998041506462215,
      "model_type": "ridge_regression"
    },
    {
      "city": "Arusha",
      "city_key": "arusha",
      "mae": 0.1769113204952872,
      "data_points": 1564,
      "next_hour_prediction": 15.245115137998173,
      "model_type": "ridge_regression"
    },
    {
      "city": "Mwanza",
      "city_key": "mwanza",
      "mae": 0.21312455684591763,
      "data_points": 1564,
      "next_hour_prediction": 20.05557841212775,
      "model_type": "ridge_regression"
    },
    {
      "city": "Zanzibar",
      "city_key": "zanzibar",
      "mae": 0.15615732489574513,
      "data_points": 1561,
      "next_hour_prediction": 22.989270355863248,
      "model_type": "ridge_regression"
    }
  ]
}