{
  "generated_at": "2026-07-17T22:20:09.164786+00:00",
  "model": "Ridge Regression (sklearn)",
  "features": [
    "hour_sin",
    "hour_cos",
    "day_sin",
    "day_cos",
    "temperature",
    "humidity",
    "pressure",
    "windspeed"
  ],
  "cities": [
    {
      "city": "Dar es Salaam",
      "city_key": "dar_es_salaam",
      "mae": 0.24613580266335397,
      "data_points": 1106,
      "next_hour_prediction": 20.468195426652386,
      "model_type": "ridge_regression"
    },
    {
      "city": "Dodoma",
      "city_key": "dodoma",
      "mae": 0.243714618924211,
      "data_points": 1151,
      "next_hour_prediction": 15.522486551179977,
      "model_type": "ridge_regression"
    },
    {
      "city": "Arusha",
      "city_key": "arusha",
      "mae": 0.2146603187750739,
      "data_points": 1156,
      "next_hour_prediction": 14.70751306022138,
      "model_type": "ridge_regression"
    },
    {
      "city": "Mwanza",
      "city_key": "mwanza",
      "mae": 0.3418513228846032,
      "data_points": 1156,
      "next_hour_prediction": 21.455483912559277,
      "model_type": "ridge_regression"
    },
    {
      "city": "Zanzibar",
      "city_key": "zanzibar",
      "mae": 0.1046155009731262,
      "data_points": 1154,
      "next_hour_prediction": 22.32288972288397,
      "model_type": "ridge_regression"
    }
  ]
}