{
  "generated_at": "2026-07-14T00:35:09.458293+00:00",
  "model": "Ridge Regression (sklearn)",
  "features": [
    "hour_sin",
    "hour_cos",
    "day_sin",
    "day_cos",
    "temperature",
    "humidity",
    "pressure",
    "windspeed"
  ],
  "cities": [
    {
      "city": "Dar es Salaam",
      "city_key": "dar_es_salaam",
      "mae": 0.5598596783814226,
      "data_points": 742,
      "next_hour_prediction": 21.083207023475502,
      "model_type": "ridge_regression"
    },
    {
      "city": "Dodoma",
      "city_key": "dodoma",
      "mae": 0.34993490237393565,
      "data_points": 776,
      "next_hour_prediction": 16.167389927354037,
      "model_type": "ridge_regression"
    },
    {
      "city": "Arusha",
      "city_key": "arusha",
      "mae": 0.3408608257065705,
      "data_points": 781,
      "next_hour_prediction": 14.15223640355988,
      "model_type": "ridge_regression"
    },
    {
      "city": "Mwanza",
      "city_key": "mwanza",
      "mae": 0.5348391935133281,
      "data_points": 781,
      "next_hour_prediction": 18.783643192980406,
      "model_type": "ridge_regression"
    },
    {
      "city": "Zanzibar",
      "city_key": "zanzibar",
      "mae": 0.36454565456528737,
      "data_points": 780,
      "next_hour_prediction": 22.96648904817398,
      "model_type": "ridge_regression"
    }
  ]
}