{
  "generated_at": "2026-07-20T17:05:08.509957+00:00",
  "model": "Ridge Regression (sklearn)",
  "features": [
    "hour_sin",
    "hour_cos",
    "day_sin",
    "day_cos",
    "temperature",
    "humidity",
    "pressure",
    "windspeed"
  ],
  "cities": [
    {
      "city": "Dar es Salaam",
      "city_key": "dar_es_salaam",
      "mae": 0.17215579954335258,
      "data_points": 1371,
      "next_hour_prediction": 23.407395335705974,
      "model_type": "ridge_regression"
    },
    {
      "city": "Dodoma",
      "city_key": "dodoma",
      "mae": 0.25442730446224804,
      "data_points": 1418,
      "next_hour_prediction": 20.353046549614387,
      "model_type": "ridge_regression"
    },
    {
      "city": "Arusha",
      "city_key": "arusha",
      "mae": 0.18857983512500293,
      "data_points": 1423,
      "next_hour_prediction": 18.295317890426265,
      "model_type": "ridge_regression"
    },
    {
      "city": "Mwanza",
      "city_key": "mwanza",
      "mae": 0.22134960518914132,
      "data_points": 1423,
      "next_hour_prediction": 22.498041858874636,
      "model_type": "ridge_regression"
    },
    {
      "city": "Zanzibar",
      "city_key": "zanzibar",
      "mae": 0.13838296331368888,
      "data_points": 1420,
      "next_hour_prediction": 23.18686552414948,
      "model_type": "ridge_regression"
    }
  ]
}