{
  "generated_at": "2026-07-12T06:35:08.473820+00:00",
  "model": "Ridge Regression (sklearn)",
  "features": [
    "hour_sin",
    "hour_cos",
    "day_sin",
    "day_cos",
    "temperature",
    "humidity",
    "pressure",
    "windspeed"
  ],
  "cities": [
    {
      "city": "Dar es Salaam",
      "city_key": "dar_es_salaam",
      "mae": 0.2748402806490252,
      "data_points": 577,
      "next_hour_prediction": 25.5579044622021,
      "model_type": "ridge_regression"
    },
    {
      "city": "Dodoma",
      "city_key": "dodoma",
      "mae": 0.4280173039285214,
      "data_points": 609,
      "next_hour_prediction": 21.148049851837847,
      "model_type": "ridge_regression"
    },
    {
      "city": "Arusha",
      "city_key": "arusha",
      "mae": 0.30235124501782407,
      "data_points": 614,
      "next_hour_prediction": 18.166682415478938,
      "model_type": "ridge_regression"
    },
    {
      "city": "Mwanza",
      "city_key": "mwanza",
      "mae": 0.3091400590495385,
      "data_points": 614,
      "next_hour_prediction": 23.50225863496334,
      "model_type": "ridge_regression"
    },
    {
      "city": "Zanzibar",
      "city_key": "zanzibar",
      "mae": 0.18900929497492314,
      "data_points": 613,
      "next_hour_prediction": 25.734926967092747,
      "model_type": "ridge_regression"
    }
  ]
}