[
  {
    "timestamp": "2026-07-18T15:20:03.128581+00:00",
    "city": "Dar es Salaam",
    "city_key": "dar_es_salaam",
    "temperature": 24.9,
    "windspeed": 13.1,
    "winddirection": 146,
    "weathercode": 3,
    "is_day": 1,
    "humidity": 44,
    "precipitation": 0.0,
    "pressure": 1015.7
  },
  {
    "timestamp": "2026-07-18T15:20:03.781642+00:00",
    "city": "Dodoma",
    "city_key": "dodoma",
    "temperature": 25.8,
    "windspeed": 12.6,
    "winddirection": 118,
    "weathercode": 2,
    "is_day": 1,
    "humidity": 23,
    "precipitation": 0.0,
    "pressure": 1015.2
  },
  {
    "timestamp": "2026-07-18T15:20:04.393719+00:00",
    "city": "Arusha",
    "city_key": "arusha",
    "temperature": 21.0,
    "windspeed": 6.0,
    "winddirection": 74,
    "weathercode": 2,
    "is_day": 1,
    "humidity": 45,
    "precipitation": 0.0,
    "pressure": 1016.6
  },
  {
    "timestamp": "2026-07-18T15:20:05.019773+00:00",
    "city": "Mwanza",
    "city_key": "mwanza",
    "temperature": 23.7,
    "windspeed": 16.1,
    "winddirection": 342,
    "weathercode": 1,
    "is_day": 1,
    "humidity": 46,
    "precipitation": 0.1,
    "pressure": 1014.2
  },
  {
    "timestamp": "2026-07-18T15:20:05.661841+00:00",
    "city": "Zanzibar",
    "city_key": "zanzibar",
    "temperature": 24.4,
    "windspeed": 17.6,
    "winddirection": 123,
    "weathercode": 3,
    "is_day": 1,
    "humidity": 65,
    "precipitation": 0.0,
    "pressure": 1016.2
  }
]