[
  {
    "city_key": "dar_es_salaam",
    "city": "Dar es Salaam",
    "predicted_at": "2026-07-06T14:06:06.088795+00:00",
    "model_type": "ridge_regression",
    "mae": 0.9848441118392659,
    "data_points": 146,
    "next_hour_prediction": 27.080764573385032,
    "forecast_7day": {
      "dates": [
        "2026-07-06",
        "2026-07-07",
        "2026-07-08",
        "2026-07-09",
        "2026-07-10",
        "2026-07-11",
        "2026-07-12"
      ],
      "temp_max": [
        29.2,
        27.0,
        28.0,
        27.4,
        27.8,
        28.2,
        29.5
      ],
      "temp_min": [
        21.3,
        23.1,
        22.4,
        21.5,
        21.3,
        21.7,
        21.4
      ],
      "precipitation": [
        0.2,
        5.3,
        6.4,
        4.0,
        2.4,
        1.5,
        0.0
      ],
      "windspeed_max": [
        19.0,
        18.2,
        17.8,
        17.7,
        16.1,
        13.6,
        12.4
      ]
    }
  },
  {
    "city_key": "dodoma",
    "city": "Dodoma",
    "predicted_at": "2026-07-06T14:06:06.091820+00:00",
    "model_type": "ridge_regression",
    "mae": 2.667438013075457,
    "data_points": 146,
    "next_hour_prediction": 28.343681539056057,
    "forecast_7day": {
      "dates": [
        "2026-07-06",
        "2026-07-07",
        "2026-07-08",
        "2026-07-09",
        "2026-07-10",
        "2026-07-11",
        "2026-07-12"
      ],
      "temp_max": [
        26.5,
        27.9,
        27.6,
        28.2,
        26.7,
        26.8,
        28.8
      ],
      "temp_min": [
        14.7,
        15.5,
        15.1,
        16.3,
        16.6,
        16.3,
        16.6
      ],
      "precipitation": [
        0.0,
        0.0,
        0.0,
        0.0,
        0.0,
        0.0,
        0.0
      ],
      "windspeed_max": [
        26.3,
        27.3,
        25.7,
        25.9,
        27.9,
        25.2,
        27.2
      ]
    }
  },
  {
    "city_key": "arusha",
    "city": "Arusha",
    "predicted_at": "2026-07-06T14:06:06.094619+00:00",
    "model_type": "ridge_regression",
    "mae": 1.4793131107949296,
    "data_points": 146,
    "next_hour_prediction": 23.0008922189394,
    "forecast_7day": {
      "dates": [
        "2026-07-06",
        "2026-07-07",
        "2026-07-08",
        "2026-07-09",
        "2026-07-10",
        "2026-07-11",
        "2026-07-12"
      ],
      "temp_max": [
        24.1,
        21.7,
        22.4,
        21.6,
        22.2,
        20.8,
        23.4
      ],
      "temp_min": [
        14.1,
        14.8,
        14.8,
        15.1,
        15.2,
        15.4,
        15.9
      ],
      "precipitation": [
        0.0,
        5.0,
        6.5,
        2.2,
        1.6,
        2.3,
        0.1
      ],
      "windspeed_max": [
        23.2,
        20.7,
        16.8,
        17.3,
        17.6,
        17.5,
        14.8
      ]
    }
  },
  {
    "city_key": "mwanza",
    "city": "Mwanza",
    "predicted_at": "2026-07-06T14:06:06.097494+00:00",
    "model_type": "ridge_regression",
    "mae": 2.150240153887611,
    "data_points": 146,
    "next_hour_prediction": 28.139827967992005,
    "forecast_7day": {
      "dates": [
        "2026-07-06",
        "2026-07-07",
        "2026-07-08",
        "2026-07-09",
        "2026-07-10",
        "2026-07-11",
        "2026-07-12"
      ],
      "temp_max": [
        29.2,
        29.1,
        28.6,
        28.4,
        28.1,
        27.2,
        25.8
      ],
      "temp_min": [
        19.0,
        19.0,
        18.9,
        19.2,
        19.3,
        20.0,
        20.5
      ],
      "precipitation": [
        0.0,
        0.0,
        0.0,
        0.0,
        0.0,
        3.0,
        1.1
      ],
      "windspeed_max": [
        21.9,
        21.8,
        19.2,
        17.1,
        14.3,
        16.7,
        12.8
      ]
    }
  },
  {
    "city_key": "zanzibar",
    "city": "Zanzibar",
    "predicted_at": "2026-07-06T14:06:06.100335+00:00",
    "model_type": "ridge_regression",
    "mae": 0.4302064790565551,
    "data_points": 146,
    "next_hour_prediction": 25.706569065036955,
    "forecast_7day": {
      "dates": [
        "2026-07-06",
        "2026-07-07",
        "2026-07-08",
        "2026-07-09",
        "2026-07-10",
        "2026-07-11",
        "2026-07-12"
      ],
      "temp_max": [
        27.9,
        26.7,
        27.0,
        27.1,
        27.3,
        27.5,
        27.5
      ],
      "temp_min": [
        22.8,
        22.5,
        22.2,
        22.5,
        21.9,
        22.6,
        21.7
      ],
      "precipitation": [
        0.1,
        5.4,
        11.2,
        3.7,
        1.8,
        0.9,
        0.9
      ],
      "windspeed_max": [
        25.0,
        24.4,
        23.6,
        22.6,
        17.9,
        17.0,
        14.8
      ]
    }
  }
]