[
  {
    "city_key": "dar_es_salaam",
    "city": "Dar es Salaam",
    "predicted_at": "2026-07-08T22:20:09.692241+00:00",
    "model_type": "ridge_regression",
    "mae": 0.4592843628506844,
    "data_points": 268,
    "next_hour_prediction": 22.119289787129805,
    "forecast_7day": {
      "dates": [
        "2026-07-09",
        "2026-07-10",
        "2026-07-11",
        "2026-07-12",
        "2026-07-13",
        "2026-07-14",
        "2026-07-15"
      ],
      "temp_max": [
        27.8,
        27.3,
        28.2,
        28.7,
        28.6,
        28.6,
        28.3
      ],
      "temp_min": [
        21.3,
        21.3,
        21.3,
        20.5,
        20.4,
        22.1,
        22.6
      ],
      "precipitation": [
        1.7,
        0.5,
        0.1,
        0.0,
        2.7,
        0.6,
        0.6
      ],
      "windspeed_max": [
        16.2,
        13.7,
        15.0,
        13.7,
        16.7,
        17.6,
        16.6
      ]
    }
  },
  {
    "city_key": "dodoma",
    "city": "Dodoma",
    "predicted_at": "2026-07-08T22:20:09.699631+00:00",
    "model_type": "ridge_regression",
    "mae": 1.8961713930382258,
    "data_points": 290,
    "next_hour_prediction": 14.614053404679236,
    "forecast_7day": {
      "dates": [
        "2026-07-09",
        "2026-07-10",
        "2026-07-11",
        "2026-07-12",
        "2026-07-13",
        "2026-07-14",
        "2026-07-15"
      ],
      "temp_max": [
        28.0,
        28.1,
        27.2,
        27.8,
        28.1,
        26.4,
        27.6
      ],
      "temp_min": [
        15.2,
        15.7,
        16.6,
        15.6,
        16.3,
        16.3,
        17.7
      ],
      "precipitation": [
        0.0,
        0.0,
        0.0,
        0.0,
        0.0,
        0.0,
        0.0
      ],
      "windspeed_max": [
        25.0,
        25.5,
        24.8,
        25.5,
        25.7,
        24.4,
        26.0
      ]
    }
  },
  {
    "city_key": "arusha",
    "city": "Arusha",
    "predicted_at": "2026-07-08T22:20:09.754233+00:00",
    "model_type": "ridge_regression",
    "mae": 0.6468195028768954,
    "data_points": 293,
    "next_hour_prediction": 15.112179208002617,
    "forecast_7day": {
      "dates": [
        "2026-07-09",
        "2026-07-10",
        "2026-07-11",
        "2026-07-12",
        "2026-07-13",
        "2026-07-14",
        "2026-07-15"
      ],
      "temp_max": [
        22.0,
        21.7,
        21.5,
        23.4,
        24.6,
        22.7,
        23.1
      ],
      "temp_min": [
        14.6,
        14.4,
        14.6,
        14.6,
        14.6,
        14.9,
        14.9
      ],
      "precipitation": [
        0.0,
        0.3,
        0.6,
        0.0,
        0.0,
        1.9,
        4.4
      ],
      "windspeed_max": [
        15.5,
        15.6,
        16.1,
        17.7,
        17.8,
        17.8,
        14.6
      ]
    }
  },
  {
    "city_key": "mwanza",
    "city": "Mwanza",
    "predicted_at": "2026-07-08T22:20:09.762039+00:00",
    "model_type": "ridge_regression",
    "mae": 0.7807915309294567,
    "data_points": 293,
    "next_hour_prediction": 20.32952174978907,
    "forecast_7day": {
      "dates": [
        "2026-07-09",
        "2026-07-10",
        "2026-07-11",
        "2026-07-12",
        "2026-07-13",
        "2026-07-14",
        "2026-07-15"
      ],
      "temp_max": [
        28.0,
        28.5,
        27.8,
        27.5,
        27.3,
        27.4,
        27.5
      ],
      "temp_min": [
        18.5,
        18.8,
        19.7,
        19.0,
        20.6,
        20.3,
        20.8
      ],
      "precipitation": [
        0.0,
        0.0,
        0.3,
        5.0,
        0.0,
        0.0,
        0.0
      ],
      "windspeed_max": [
        17.9,
        13.7,
        14.0,
        13.8,
        11.5,
        12.7,
        18.0
      ]
    }
  },
  {
    "city_key": "zanzibar",
    "city": "Zanzibar",
    "predicted_at": "2026-07-08T22:20:09.769242+00:00",
    "model_type": "ridge_regression",
    "mae": 0.5907306645034437,
    "data_points": 293,
    "next_hour_prediction": 22.904962976807102,
    "forecast_7day": {
      "dates": [
        "2026-07-09",
        "2026-07-10",
        "2026-07-11",
        "2026-07-12",
        "2026-07-13",
        "2026-07-14",
        "2026-07-15"
      ],
      "temp_max": [
        27.5,
        27.4,
        27.1,
        27.3,
        27.7,
        27.6,
        26.9
      ],
      "temp_min": [
        22.7,
        21.9,
        21.9,
        21.4,
        22.0,
        23.0,
        22.7
      ],
      "precipitation": [
        1.2,
        1.7,
        1.5,
        0.3,
        0.9,
        1.8,
        2.4
      ],
      "windspeed_max": [
        22.3,
        15.8,
        16.5,
        17.5,
        20.2,
        24.4,
        22.5
      ]
    }
  }
]