[
  {
    "city_key": "dar_es_salaam",
    "city": "Dar es Salaam",
    "predicted_at": "2026-07-11T12:20:09.358263+00:00",
    "model_type": "ridge_regression",
    "mae": 0.61822771258857,
    "data_points": 504,
    "next_hour_prediction": 25.617882315020015,
    "forecast_7day": {}
  },
  {
    "city_key": "dodoma",
    "city": "Dodoma",
    "predicted_at": "2026-07-11T12:20:09.370206+00:00",
    "model_type": "ridge_regression",
    "mae": 0.46767051384985997,
    "data_points": 537,
    "next_hour_prediction": 26.034057985039336,
    "forecast_7day": {
      "dates": [
        "2026-07-11",
        "2026-07-12",
        "2026-07-13",
        "2026-07-14",
        "2026-07-15",
        "2026-07-16",
        "2026-07-17"
      ],
      "temp_max": [
        26.8,
        28.5,
        27.5,
        26.5,
        26.8,
        26.1,
        27.2
      ],
      "temp_min": [
        16.1,
        15.4,
        16.0,
        15.6,
        15.8,
        15.7,
        15.7
      ],
      "precipitation": [
        0.0,
        0.0,
        0.0,
        0.0,
        0.0,
        0.0,
        0.0
      ],
      "windspeed_max": [
        23.8,
        26.4,
        26.6,
        26.8,
        25.3,
        26.9,
        27.0
      ]
    }
  },
  {
    "city_key": "arusha",
    "city": "Arusha",
    "predicted_at": "2026-07-11T12:20:09.381905+00:00",
    "model_type": "ridge_regression",
    "mae": 0.2945551777354925,
    "data_points": 541,
    "next_hour_prediction": 21.13115889262639,
    "forecast_7day": {
      "dates": [
        "2026-07-11",
        "2026-07-12",
        "2026-07-13",
        "2026-07-14",
        "2026-07-15",
        "2026-07-16",
        "2026-07-17"
      ],
      "temp_max": [
        21.8,
        22.6,
        23.4,
        22.4,
        23.5,
        22.3,
        23.5
      ],
      "temp_min": [
        14.0,
        14.7,
        15.2,
        14.6,
        14.5,
        14.9,
        14.1
      ],
      "precipitation": [
        1.4,
        0.7,
        0.0,
        0.2,
        2.7,
        0.0,
        0.0
      ],
      "windspeed_max": [
        13.8,
        15.6,
        17.6,
        17.2,
        16.5,
        16.8,
        18.5
      ]
    }
  },
  {
    "city_key": "mwanza",
    "city": "Mwanza",
    "predicted_at": "2026-07-11T12:20:09.393244+00:00",
    "model_type": "ridge_regression",
    "mae": 0.5394256805304841,
    "data_points": 541,
    "next_hour_prediction": 25.73266516146546,
    "forecast_7day": {
      "dates": [
        "2026-07-11",
        "2026-07-12",
        "2026-07-13",
        "2026-07-14",
        "2026-07-15",
        "2026-07-16",
        "2026-07-17"
      ],
      "temp_max": [
        27.7,
        27.1,
        28.3,
        28.1,
        28.0,
        28.3,
        27.0
      ],
      "temp_min": [
        19.1,
        18.7,
        19.8,
        19.9,
        19.7,
        21.1,
        20.1
      ],
      "precipitation": [
        1.0,
        3.5,
        0.7,
        0.5,
        0.3,
        0.3,
        0.6
      ],
      "windspeed_max": [
        15.6,
        17.1,
        16.1,
        15.0,
        17.2,
        19.6,
        16.6
      ]
    }
  },
  {
    "city_key": "zanzibar",
    "city": "Zanzibar",
    "predicted_at": "2026-07-11T12:20:09.464611+00:00",
    "model_type": "ridge_regression",
    "mae": 0.5196993084071114,
    "data_points": 540,
    "next_hour_prediction": 26.133783295772844,
    "forecast_7day": {
      "dates": [
        "2026-07-11",
        "2026-07-12",
        "2026-07-13",
        "2026-07-14",
        "2026-07-15",
        "2026-07-16",
        "2026-07-17"
      ],
      "temp_max": [
        27.3,
        27.2,
        27.5,
        27.5,
        27.3,
        27.3,
        26.9
      ],
      "temp_min": [
        22.9,
        22.0,
        21.8,
        22.6,
        22.9,
        22.6,
        22.7
      ],
      "precipitation": [
        1.0,
        1.5,
        0.2,
        1.7,
        1.2,
        1.8,
        0.9
      ],
      "windspeed_max": [
        13.2,
        16.3,
        18.8,
        24.8,
        22.1,
        24.0,
        24.0
      ]
    }
  }
]